grablib/__init__.py
grablib/build.py
grablib/cli.py
grablib/common.py
grablib/download.py
grablib/grab.py
grablib/version.py
grablib-0.8.dist-info/LICENSE
grablib-0.8.dist-info/METADATA
grablib-0.8.dist-info/WHEEL
grablib-0.8.dist-info/entry_points.txt
grablib-0.8.dist-info/top_level.txt
grablib-0.8.dist-info/zip-safe
grablib-0.8.dist-info/RECORD
