Metadata-Version: 2.1
Name: grablib
Version: 0.8
Summary: Utility for defining then downloading and preprocessing external static files.
Home-page: https://github.com/samuelcolvin/grablib
Author: Samuel Colvin
Author-email: S@muelColvin.com
License: MIT
Keywords: css,sass,scss,build,static,download
Platform: any
Classifier: Environment :: Console
Classifier: Environment :: Web Environment
Classifier: Intended Audience :: Developers
Classifier: License :: OSI Approved :: MIT License
Classifier: Programming Language :: Python
Classifier: Programming Language :: Python :: 3
Classifier: Programming Language :: Python :: 3.6
Classifier: Programming Language :: Python :: 3.7
Classifier: Programming Language :: Python :: Implementation :: CPython
Requires-Python: >=3.6
Requires-Dist: click (>=6.6)
Requires-Dist: ruamel.yaml (>=0.15.37)
Requires-Dist: requests (>=2.20)
Provides-Extra: build
Requires-Dist: jsmin (>=2.2.1) ; extra == 'build'
Requires-Dist: libsass (>=0.14.4) ; extra == 'build'
